django_teamized-0.1.2.dist-info/licenses/LICENSE
teamized/__init__.py
teamized/admin.py
teamized/apps.py
teamized/decorators.py
teamized/enums.py
teamized/exceptions.py
teamized/models.py
teamized/options.py
teamized/tests.py
teamized/urls.py
teamized/utils.py
teamized/validation.py
teamized/views.py
teamized/api/__init__.py
teamized/api/urls.py
teamized/api/endpoints/__init__.py
teamized/api/endpoints/calendar.py
teamized/api/endpoints/club.py
teamized/api/endpoints/club_attendance.py
teamized/api/endpoints/main.py
teamized/api/endpoints/todo.py
teamized/api/endpoints/workingtime.py
teamized/api/utils/__init__.py
teamized/api/utils/admin.py
teamized/api/utils/constants.py
teamized/api/utils/decorators.py
teamized/api/utils/models.py
teamized/club/__init__.py
teamized/club/admin.py
teamized/club/decorators.py
teamized/club/models.py
teamized/club/urls.py
teamized/club/views.py
teamized/club/api/__init__.py
teamized/club/api/urls.py
teamized/club/api/views.py
teamized/management/commands/teamized_build.py
teamized/migrations/0001_squashed_initial.py
teamized/migrations/0002_renamed_app_to_teamized.py
teamized/migrations/0003_basic_club_models.py
teamized/migrations/0004_clubmember_portfolio_biography_and_more.py
teamized/migrations/0005_user_max_owned_teams_override_alter_user_auth_user_and_more.py
teamized/migrations/0006_clubmembergroup_shared_uid.py
teamized/migrations/0007_remove_clubmembermagiclink_logged_in_and_more.py
teamized/migrations/0008_clubattendanceevent_clubattendanceeventparticipation.py
teamized/migrations/__init__.py
teamized/static/teamized/favicon.ico
teamized/static/teamized/app/128.mainapp.js
teamized/static/teamized/app/170.mainapp.js
teamized/static/teamized/app/22.mainapp.js
teamized/static/teamized/app/336.mainapp.js
teamized/static/teamized/app/336.mainapp.js.LICENSE.txt
teamized/static/teamized/app/376.mainapp.js
teamized/static/teamized/app/400.mainapp.js
teamized/static/teamized/app/400.mainapp.js.LICENSE.txt
teamized/static/teamized/app/575.mainapp.js
django_teamized-0.1.2.dist-info/METADATA
django_teamized-0.1.2.dist-info/WHEEL
django_teamized-0.1.2.dist-info/top_level.txt
django_teamized-0.1.2.dist-info/RECORD
