Metadata-Version: 2.4
Name: django-teamized
Version: 0.1.2
Summary: Ein Tool für Zeitmanagement und Projektplanung
Author-email: Rafael Urben <github@rafaelurben.ch>
Maintainer-email: Rafael Urben <github@rafaelurben.ch>
Project-URL: Homepage, https://github.com/rafaelurben/django-teamized
Project-URL: Docs, https://github.com/rafaelurben/django-teamized#readme
Project-URL: GitHub, https://github.com/rafaelurben/django-teamized
Project-URL: Issues, https://github.com/rafaelurben/django-teamized/issues
Project-URL: Funding, https://github.com/sponsors/rafaelurben
Classifier: Environment :: Web Environment
Classifier: Framework :: Django
Classifier: Framework :: Django :: 4.2
Classifier: Framework :: Django :: 5.0
Classifier: Framework :: Django :: 5.1
Classifier: Framework :: Django :: 5.2
Classifier: Intended Audience :: Developers
Classifier: Operating System :: OS Independent
Classifier: Programming Language :: Python
Classifier: Programming Language :: Python :: 3
Classifier: Programming Language :: Python :: 3 :: Only
Classifier: Programming Language :: Python :: 3.10
Classifier: Programming Language :: Python :: 3.11
Classifier: Programming Language :: Python :: 3.12
Classifier: Programming Language :: Python :: 3.13
Classifier: Topic :: Internet :: WWW/HTTP
Classifier: Topic :: Internet :: WWW/HTTP :: Dynamic Content
Requires-Python: >=3.10
License-File: LICENSE
Requires-Dist: Django>=4.2
Dynamic: license-file
